seclea_ai/__init__.py
seclea_ai/authentication.py
seclea_ai/dataset_utils.py
seclea_ai/exceptions.py
seclea_ai/seclea_ai.py
seclea_ai/storage.py
seclea_ai/transformations.py
seclea_ai/lib/__init__.py
seclea_ai/lib/seclea_utils/__init__.py
seclea_ai/lib/seclea_utils/clib/pigz.exe
seclea_ai/lib/seclea_utils/clib/pigz/Makefile
seclea_ai/lib/seclea_utils/clib/pigz/README
seclea_ai/lib/seclea_utils/clib/pigz/pigz.1
seclea_ai/lib/seclea_utils/clib/pigz/pigz.c
seclea_ai/lib/seclea_utils/clib/pigz/pigz.pdf
seclea_ai/lib/seclea_utils/clib/pigz/try.c
seclea_ai/lib/seclea_utils/clib/pigz/try.h
seclea_ai/lib/seclea_utils/clib/pigz/yarn.c
seclea_ai/lib/seclea_utils/clib/pigz/yarn.h
seclea_ai/lib/seclea_utils/clib/pigz/zopfli/CONTRIBUTING.md
seclea_ai/lib/seclea_utils/clib/pigz/zopfli/CONTRIBUTORS
seclea_ai/lib/seclea_utils/clib/pigz/zopfli/COPYING
seclea_ai/lib/seclea_utils/clib/pigz/zopfli/README
seclea_ai/lib/seclea_utils/clib/pigz/zopfli/src/zopfli/blocksplitter.c
seclea_ai/lib/seclea_utils/clib/pigz/zopfli/src/zopfli/blocksplitter.h
seclea_ai/lib/seclea_utils/clib/pigz/zopfli/src/zopfli/cache.c
seclea_ai/lib/seclea_utils/clib/pigz/zopfli/src/zopfli/cache.h
seclea_ai/lib/seclea_utils/clib/pigz/zopfli/src/zopfli/deflate.c
seclea_ai/lib/seclea_utils/clib/pigz/zopfli/src/zopfli/deflate.h
seclea_ai/lib/seclea_utils/clib/pigz/zopfli/src/zopfli/hash.c
seclea_ai/lib/seclea_utils/clib/pigz/zopfli/src/zopfli/hash.h
seclea_ai/lib/seclea_utils/clib/pigz/zopfli/src/zopfli/katajainen.c
seclea_ai/lib/seclea_utils/clib/pigz/zopfli/src/zopfli/katajainen.h
seclea_ai/lib/seclea_utils/clib/pigz/zopfli/src/zopfli/lz77.c
seclea_ai/lib/seclea_utils/clib/pigz/zopfli/src/zopfli/lz77.h
seclea_ai/lib/seclea_utils/clib/pigz/zopfli/src/zopfli/squeeze.c
seclea_ai/lib/seclea_utils/clib/pigz/zopfli/src/zopfli/squeeze.h
seclea_ai/lib/seclea_utils/clib/pigz/zopfli/src/zopfli/symbols.c
seclea_ai/lib/seclea_utils/clib/pigz/zopfli/src/zopfli/symbols.h
seclea_ai-1.1.0.dist-info/LICENSE.txt
seclea_ai-1.1.0.dist-info/METADATA
seclea_ai-1.1.0.dist-info/WHEEL
seclea_ai-1.1.0.dist-info/top_level.txt
seclea_ai-1.1.0.dist-info/RECORD
