Metadata-Version: 2.1
Name: seclea-ai
Version: 1.1.0
Summary: Seclea integration.
Home-page: https://github.com/seclea/seclea_ai
Author: octavio
Author-email: octavio.delser@gmail.com
License: UNKNOWN
Platform: UNKNOWN
Classifier: Programming Language :: Python :: 3
Classifier: License :: OSI Approved :: MIT License
Classifier: Operating System :: OS Independent
Requires-Python: >=3.7
Requires-Dist: dill (>=0.3.4)
Requires-Dist: decorator
Requires-Dist: joblib
Requires-Dist: pandas (>=1.3.0)
Requires-Dist: pickleDB (>=0.9.2)
Requires-Dist: requests (>=2.0.0)
Requires-Dist: wrapt
